NeutroSpecUI/__init__.py
NeutroSpecUI/__main__.py
NeutroSpecUI/app.py
NeutroSpecUI/data_models.py
NeutroSpecUI/experiment_manager.py
NeutroSpecUI/experimental_setup.py
NeutroSpecUI/main_window.py
NeutroSpecUI/material_widget.py
NeutroSpecUI/plot.py
NeutroSpecUI/py.typed
NeutroSpecUI/read_file.py
NeutroSpecUI/recent_files_menu.py
NeutroSpecUI/simulate.py
NeutroSpecUI/static_params.py
NeutroSpecUI/backends/__init__.py
NeutroSpecUI/backends/neutro/__init__.py
NeutroSpecUI/backends/neutro/plot.py
NeutroSpecUI/backends/neutro/simulation.py
NeutroSpecUI/widgets/parameter_details.py
NeutroSpecUI/widgets/select_button.py
NeutroSpecUI/widgets/settings_dialog.py
neutrospecui-1.1.0.dist-info/LICENSE
neutrospecui-1.1.0.dist-info/METADATA
neutrospecui-1.1.0.dist-info/WHEEL
neutrospecui-1.1.0.dist-info/top_level.txt
neutrospecui-1.1.0.dist-info/RECORD
