Metadata-Version: 2.2
Name: NeutroSpecUI
Version: 1.1.0
Summary: A package for the analysis of Neutron X-ray Spectroscopy data
Author: Mitra Nassermostofi, Luisa Haussner, Elina Lickes, Benedikt Bletz, Sebastian Braun
License: MIT License
Project-URL: Homepage, https://github.com/Aseraphyss/NeutroSpecUI
Project-URL: Issues, https://github.com/Aseraphyss/NeutroSpecUI/issues
Keywords: neutron,x-ray,spectroscopy,analysis
Classifier: Programming Language :: Python :: 3
Classifier: License :: OSI Approved :: MIT License
Classifier: Operating System :: OS Independent
Requires-Python: >=3.10
License-File: LICENSE
Requires-Dist: numpy
Requires-Dist: scipy
Requires-Dist: pandas
Requires-Dist: matplotlib
Requires-Dist: PySide6
Provides-Extra: dev
Requires-Dist: pytest-sugar; extra == "dev"
Requires-Dist: NeutroSpecUI[test]; extra == "dev"
Provides-Extra: test
Requires-Dist: tox; extra == "test"
Requires-Dist: pytest; extra == "test"
Requires-Dist: pytest-cov; extra == "test"
Requires-Dist: pytest-mock; extra == "test"
Requires-Dist: pytest-qt; extra == "test"
Requires-Dist: pytest-xvfb; extra == "test"
Requires-Dist: hypothesis; extra == "test"
Requires-Dist: mypy; extra == "test"
Requires-Dist: black; extra == "test"
